areshook/__init__.py
areshook/_exceptions.py
areshook/_frida.py
areshook/_modules.py
areshook-0.1.3.3.dist-info/METADATA
areshook-0.1.3.3.dist-info/WHEEL
areshook-0.1.3.3.dist-info/top_level.txt
areshook-0.1.3.3.dist-info/RECORD
