Metadata-Version: 2.1
Name: areshook
Version: 0.1.3.3
Summary: A simple hook library.
Author: 369
Author-email: luck.yangbo@gmail.com
Classifier: Programming Language :: Python :: 3
Classifier: License :: OSI Approved :: MIT License
Classifier: Operating System :: OS Independent
Requires-Dist: frida
Requires-Dist: frida-tools
Requires-Dist: heradata
Requires-Dist: pydantic
